discordstatus/__init__.py
discordstatus/discordstatus.py
tests/__init__.py
tests/test_discordstatus.py
DiscordStatus-0.0.2.dist-info/LICENSE
DiscordStatus-0.0.2.dist-info/METADATA
DiscordStatus-0.0.2.dist-info/WHEEL
DiscordStatus-0.0.2.dist-info/top_level.txt
DiscordStatus-0.0.2.dist-info/RECORD
