Metadata-Version: 2.1
Name: DiscordStatus
Version: 0.0.2
Summary: A wrapper for talking to the Discord Status page's API
Home-page: https://github.com/SomewhatDamaged/discordstatus
Author: Byron Mulvogue
Author-email: not.2.me.damaged@gmail.com
License: UNKNOWN
Platform: UNKNOWN
Classifier: Programming Language :: Python :: 3
Classifier: License :: OSI Approved :: MIT License
Classifier: Operating System :: OS Independent
Requires-Python: >=3.6
Requires-Dist: requests
